spherpro/__init__.py
spherpro/bro.py
spherpro/configuration.py
spherpro/datastore.py
spherpro/db.py
spherpro/library.py
spherpro/bromodules/__init__.py
spherpro/bromodules/filter_base.py
spherpro/bromodules/filter_measurements.py
spherpro/bromodules/filter_membership.py
spherpro/bromodules/filter_objectfilters.py
spherpro/bromodules/filters.py
spherpro/bromodules/helpers.py
spherpro/bromodules/helpers_anndata.py
spherpro/bromodules/helpers_varia.py
spherpro/bromodules/helpers_vz.py
spherpro/bromodules/io.py
spherpro/bromodules/io_anndata.py
spherpro/bromodules/io_base.py
spherpro/bromodules/io_imcfolder.py
spherpro/bromodules/io_masks.py
spherpro/bromodules/io_stackimage.py
spherpro/bromodules/plot_base.py
spherpro/bromodules/plot_condition_images.py
spherpro/bromodules/plot_debarcodequality.py
spherpro/bromodules/plot_heatmask.py
spherpro/bromodules/plot_image.py
spherpro/bromodules/plot_scatterplot.py
spherpro/bromodules/plots.py
spherpro/bromodules/processing.py
spherpro/bromodules/processing_debarcoding.py
spherpro/bromodules/processing_dist_rim.py
spherpro/bromodules/processing_measurementmaker.py
spherpro/bromodules/processing_nb_agg.py
spherpro-0.1.5.dist-info/LICENSE
spherpro-0.1.5.dist-info/METADATA
spherpro-0.1.5.dist-info/WHEEL
spherpro-0.1.5.dist-info/top_level.txt
spherpro-0.1.5.dist-info/RECORD
