Metadata-Version: 2.1
Name: spherpro
Version: 0.1.5
Summary: Tool to analize tumor spheroid data
Home-page: https://github.com/bodenmillerlab/spherpro
Author: Vito Zanotelli, Matthias Leutenegger, Bodenmiller Lab UZH
Author-email: vito.zanotelli@uzh.ch
License: BSD-3 License
Platform: UNKNOWN
Requires-Dist: anndata
Requires-Dist: colorcet
Requires-Dist: imctools (==1.0.7)
Requires-Dist: matplotlib
Requires-Dist: numpy
Requires-Dist: pandas
Requires-Dist: pyyaml
Requires-Dist: requests
Requires-Dist: scikit-image
Requires-Dist: scikit-learn
Requires-Dist: scipy
Requires-Dist: seaborn
Requires-Dist: sqlalchemy
Requires-Dist: tifffile
Requires-Dist: sphinx (==3.2.1)
Requires-Dist: plotnine
Requires-Dist: matplotlib-scalebar
Requires-Dist: pycytools (>0.6)
Requires-Dist: ipywidgets
